Metadata-Version: 2.1
Name: mec-jun2023
Version: 1.0.4
Summary: description of the package
Home-page: 
Author-email: ag133@nyu.edu
License: GNU
Requires-Python: >= 3
License-File: LICENSE
